{
  "schema_version": 2,
  "meta": {
    "generated_at": "2026-06-07T13:25:55.420717+02:00",
    "engine": "velora-pro-2",
    "match_count": 5
  },
  "matchs": [
    {
      "id_match": "71421980",
      "date_match": "07/06/2026 à 18:30",
      "match_start_ts": 1780849800,
      "match_status": "PREMATCH",
      "equipe_domicile": "Danemark",
      "equipe_exterieur": "Ukraine",
      "meta_match": {
        "competition": {
          "name": "International — Matchs Amicaux",
          "type": "friendly",
          "stakes_tier": "low",
          "category_id": "4",
          "tournament_id": "66"
        }
      },
      "confidence": {
        "velora_score": 52.0,
        "indice_velora": 2,
        "base_confidence": 0.52,
        "adjusted_confidence": 0.22,
        "modifiers": [
          {
            "code": "friendly_match",
            "delta": -0.3,
            "label": "Match amical — confiance réduite"
          }
        ]
      },
      "pro_alerts": [],
      "free_analysis": {
        "cotes_1n2": {
          "1": 1.66,
          "N": 3.5,
          "2": 4.4
        },
        "probabilites": {
          "1": 42,
          "N": 25,
          "2": 33
        },
        "probabilites_marche": {
          "1": 54,
          "N": 26,
          "2": 20
        },
        "pronostic_1n2": "2",
        "pronostic_label": "Victoire Ukraine",
        "confiance_niveau": "faible",
        "line_signal": "stable",
        "poisson_lambdas": {
          "home": 2.251,
          "away": 1.37
        },
        "top_scores_modele": [
          {
            "score": "1-2",
            "prob": 6
          },
          {
            "score": "0-1",
            "prob": 4
          },
          {
            "score": "2-3",
            "prob": 3
          },
          {
            "score": "1-3",
            "prob": 3
          },
          {
            "score": "0-2",
            "prob": 3
          }
        ],
        "prob_over_25_modele": 69,
        "prob_btts_modele": 66,
        "football_data_enriched": true,
        "markets_raw": {
          "over_under_total": {},
          "team_goals": {}
        },
        "value_bets": [
          {
            "market": "1n2",
            "pick": "2",
            "label": "Victoire Ukraine",
            "cote": 4.4,
            "edge": 1.452,
            "stars": 5,
            "is_primary": true
          }
        ],
        "primary_pick": {
          "market": "1n2",
          "pick": "2",
          "label": "Victoire Ukraine",
          "cote": 4.4,
          "conseil_short": "🔥 Value Bet — Victoire Ukraine @ 4.40"
        },
        "display_badges": []
      },
      "premium_analysis": {
        "score_exact": {
          "top3": []
        },
        "buteur_match": {
          "top": []
        },
        "buteur_mi_temps": {
          "top": []
        },
        "buteur_double": {
          "top": []
        },
        "value_bets": []
      },
      "_legacy": {
        "conseil": "Victoire Ukraine — forme favorable Ukraine",
        "tendance_buts": "Match Offensif",
        "marches_supplementaires": {},
        "opportunite_type": "1n2",
        "is_opportunite": true
      }
    },
    {
      "id_match": "68686010",
      "date_match": "07/06/2026 à 20:00",
      "match_start_ts": 1780855200,
      "match_status": "PREMATCH",
      "equipe_domicile": "Inter Toronto",
      "equipe_exterieur": "Forge",
      "meta_match": {
        "competition": {
          "name": "Canada — Canadian Premier League",
          "type": "league",
          "round": "J1",
          "stakes_tier": "medium",
          "category_id": "388",
          "tournament_id": "80244"
        }
      },
      "confidence": {
        "velora_score": 67.2,
        "indice_velora": 3,
        "base_confidence": 0.672,
        "adjusted_confidence": 0.672,
        "modifiers": []
      },
      "pro_alerts": [],
      "free_analysis": {
        "cotes_1n2": {
          "1": 2.95,
          "N": 3.25,
          "2": 1.96
        },
        "probabilites": {
          "1": 23,
          "N": 23,
          "2": 54
        },
        "probabilites_marche": {
          "1": 29,
          "N": 27,
          "2": 44
        },
        "pronostic_1n2": "2",
        "pronostic_label": "Victoire Forge",
        "confiance_niveau": "haute",
        "line_signal": "stable",
        "poisson_lambdas": {
          "home": 1.834,
          "away": 2.259
        },
        "top_scores_modele": [
          {
            "score": "1-2",
            "prob": 8
          },
          {
            "score": "1-3",
            "prob": 6
          },
          {
            "score": "2-3",
            "prob": 5
          },
          {
            "score": "0-2",
            "prob": 4
          },
          {
            "score": "0-1",
            "prob": 4
          }
        ],
        "prob_over_25_modele": 76,
        "prob_btts_modele": 74,
        "football_data_enriched": true,
        "markets_raw": {
          "over_under_total": {},
          "team_goals": {}
        },
        "value_bets": [
          {
            "market": "1n2",
            "pick": "2",
            "label": "Victoire Forge",
            "cote": 1.96,
            "edge": 1.058,
            "stars": 2,
            "is_primary": true
          }
        ],
        "primary_pick": {
          "market": "1n2",
          "pick": "2",
          "label": "Victoire Forge",
          "cote": 1.96,
          "conseil_short": "🔥 Value Bet — Victoire Forge @ 1.96"
        },
        "display_badges": []
      },
      "premium_analysis": {
        "score_exact": {
          "top3": []
        },
        "buteur_match": {
          "top": []
        },
        "buteur_mi_temps": {
          "top": []
        },
        "buteur_double": {
          "top": []
        },
        "value_bets": []
      },
      "_legacy": {
        "conseil": "Victoire Forge — forme favorable Forge — Classement 3e vs 1e",
        "tendance_buts": "Match Offensif",
        "marches_supplementaires": {},
        "opportunite_type": "1n2",
        "is_opportunite": true
      }
    },
    {
      "id_match": "71170368",
      "date_match": "07/06/2026 à 21:00",
      "match_start_ts": 1780858800,
      "match_status": "PREMATCH",
      "equipe_domicile": "Maroc",
      "equipe_exterieur": "Norvège",
      "meta_match": {
        "competition": {
          "name": "International — Matchs Amicaux",
          "type": "friendly",
          "stakes_tier": "low",
          "category_id": "4",
          "tournament_id": "66"
        }
      },
      "confidence": {
        "velora_score": 56.4,
        "indice_velora": 3,
        "base_confidence": 0.564,
        "adjusted_confidence": 0.264,
        "modifiers": [
          {
            "code": "friendly_match",
            "delta": -0.3,
            "label": "Match amical — confiance réduite"
          }
        ]
      },
      "pro_alerts": [],
      "free_analysis": {
        "cotes_1n2": {
          "1": 3.0,
          "N": 3.45,
          "2": 2.15
        },
        "probabilites": {
          "1": 40,
          "N": 26,
          "2": 34
        },
        "probabilites_marche": {
          "1": 31,
          "N": 27,
          "2": 42
        },
        "pronostic_1n2": "1",
        "pronostic_label": "Victoire Maroc",
        "confiance_niveau": "faible",
        "line_signal": "stable",
        "poisson_lambdas": {
          "home": 1.688,
          "away": 1.965
        },
        "top_scores_modele": [
          {
            "score": "2-1",
            "prob": 7
          },
          {
            "score": "1-0",
            "prob": 4
          },
          {
            "score": "3-1",
            "prob": 4
          },
          {
            "score": "3-2",
            "prob": 4
          },
          {
            "score": "2-0",
            "prob": 4
          }
        ],
        "prob_over_25_modele": 70,
        "prob_btts_modele": 70,
        "football_data_enriched": true,
        "markets_raw": {
          "over_under_total": {},
          "team_goals": {}
        },
        "value_bets": [
          {
            "market": "1n2",
            "pick": "1",
            "label": "Victoire Maroc",
            "cote": 3.0,
            "edge": 1.2,
            "stars": 5,
            "is_primary": true
          }
        ],
        "primary_pick": {
          "market": "1n2",
          "pick": "1",
          "label": "Victoire Maroc",
          "cote": 3.0,
          "conseil_short": "🔥 Value Bet — Victoire Maroc @ 3.00"
        },
        "display_badges": []
      },
      "premium_analysis": {
        "score_exact": {
          "top3": []
        },
        "buteur_match": {
          "top": []
        },
        "buteur_mi_temps": {
          "top": []
        },
        "buteur_double": {
          "top": []
        },
        "value_bets": []
      },
      "_legacy": {
        "conseil": "Victoire Maroc — forme favorable Maroc",
        "tendance_buts": "Match Offensif",
        "marches_supplementaires": {},
        "opportunite_type": "1n2",
        "is_opportunite": true
      }
    },
    {
      "id_match": "71422646",
      "date_match": "07/06/2026 à 21:00",
      "match_start_ts": 1780858800,
      "match_status": "PREMATCH",
      "equipe_domicile": "Grèce",
      "equipe_exterieur": "Italie",
      "meta_match": {
        "competition": {
          "name": "International — Matchs Amicaux",
          "type": "friendly",
          "stakes_tier": "low",
          "category_id": "4",
          "tournament_id": "66"
        }
      },
      "confidence": {
        "velora_score": 49.9,
        "indice_velora": 2,
        "base_confidence": 0.499,
        "adjusted_confidence": 0.199,
        "modifiers": [
          {
            "code": "friendly_match",
            "delta": -0.3,
            "label": "Match amical — confiance réduite"
          }
        ]
      },
      "pro_alerts": [],
      "free_analysis": {
        "cotes_1n2": {
          "1": 2.05,
          "N": 3.45,
          "2": 3.1
        },
        "probabilites": {
          "1": 37,
          "N": 26,
          "2": 37
        },
        "probabilites_marche": {
          "1": 45,
          "N": 26,
          "2": 29
        },
        "pronostic_1n2": "2",
        "pronostic_label": "Victoire Italie",
        "confiance_niveau": "faible",
        "line_signal": "stable",
        "poisson_lambdas": {
          "home": 1.991,
          "away": 1.598
        },
        "top_scores_modele": [
          {
            "score": "1-2",
            "prob": 7
          },
          {
            "score": "0-1",
            "prob": 4
          },
          {
            "score": "1-3",
            "prob": 4
          },
          {
            "score": "2-3",
            "prob": 4
          },
          {
            "score": "0-2",
            "prob": 4
          }
        ],
        "prob_over_25_modele": 69,
        "prob_btts_modele": 68,
        "football_data_enriched": true,
        "markets_raw": {
          "over_under_total": {},
          "team_goals": {}
        },
        "value_bets": [
          {
            "market": "1n2",
            "pick": "2",
            "label": "Victoire Italie",
            "cote": 3.1,
            "edge": 1.147,
            "stars": 4,
            "is_primary": true
          }
        ],
        "primary_pick": {
          "market": "1n2",
          "pick": "2",
          "label": "Victoire Italie",
          "cote": 3.1,
          "conseil_short": "🔥 Value Bet — Victoire Italie @ 3.10"
        },
        "display_badges": []
      },
      "premium_analysis": {
        "score_exact": {
          "top3": []
        },
        "buteur_match": {
          "top": []
        },
        "buteur_mi_temps": {
          "top": []
        },
        "buteur_double": {
          "top": []
        },
        "value_bets": []
      },
      "_legacy": {
        "conseil": "Victoire Italie — forme favorable Italie",
        "tendance_buts": "Match Offensif",
        "marches_supplementaires": {},
        "opportunite_type": "1n2",
        "is_opportunite": true
      }
    },
    {
      "id_match": "71853280",
      "date_match": "07/06/2026 à 21:00",
      "match_start_ts": 1780858800,
      "match_status": "PREMATCH",
      "equipe_domicile": "Las Palmas",
      "equipe_exterieur": "Malaga",
      "meta_match": {
        "competition": {
          "name": "Espagne — LaLiga2",
          "type": "league",
          "round": "1/2 aller",
          "stakes_tier": "medium",
          "category_id": "32",
          "tournament_id": "16255"
        }
      },
      "confidence": {
        "velora_score": 56.4,
        "indice_velora": 3,
        "base_confidence": 0.564,
        "adjusted_confidence": 0.564,
        "modifiers": []
      },
      "pro_alerts": [],
      "free_analysis": {
        "cotes_1n2": {
          "1": 1.98,
          "N": 3.0,
          "2": 3.3
        },
        "probabilites": {
          "1": 33,
          "N": 29,
          "2": 38
        },
        "probabilites_marche": {
          "1": 44,
          "N": 29,
          "2": 27
        },
        "pronostic_1n2": "2",
        "pronostic_label": "Victoire Malaga",
        "confiance_niveau": "haute",
        "line_signal": "stable",
        "poisson_lambdas": {
          "home": 1.326,
          "away": 1.039
        },
        "top_scores_modele": [
          {
            "score": "0-1",
            "prob": 10
          },
          {
            "score": "1-2",
            "prob": 7
          },
          {
            "score": "0-2",
            "prob": 5
          },
          {
            "score": "1-3",
            "prob": 2
          },
          {
            "score": "0-3",
            "prob": 2
          }
        ],
        "prob_over_25_modele": 42,
        "prob_btts_modele": 47,
        "football_data_enriched": true,
        "markets_raw": {
          "over_under_total": {},
          "team_goals": {}
        },
        "value_bets": [
          {
            "market": "1n2",
            "pick": "2",
            "label": "Victoire Malaga",
            "cote": 3.3,
            "edge": 1.254,
            "stars": 5,
            "is_primary": true
          },
          {
            "market": "dc_x2",
            "pick": "dc_x2",
            "label": "Double chance X2",
            "edge": 1.254,
            "stars": 5,
            "is_primary": false
          }
        ],
        "primary_pick": {
          "market": "1n2",
          "pick": "2",
          "label": "Victoire Malaga",
          "cote": 3.3,
          "conseil_short": "🔥 Value Bet — Victoire Malaga @ 3.30"
        },
        "display_badges": []
      },
      "premium_analysis": {
        "score_exact": {
          "top3": []
        },
        "buteur_match": {
          "top": []
        },
        "buteur_mi_temps": {
          "top": []
        },
        "buteur_double": {
          "top": []
        },
        "value_bets": []
      },
      "_legacy": {
        "conseil": "Victoire Malaga — forme favorable Malaga — Classement 5e vs 4e",
        "tendance_buts": "Match Offensif",
        "marches_supplementaires": {},
        "opportunite_type": "1n2",
        "is_opportunite": true
      }
    }
  ]
}
